gcpy/__init__.py
gcpy/_version.py
gcpy/append_grid_corners.py
gcpy/bpch_to_nc_names.yml
gcpy/constants.py
gcpy/cstools.py
gcpy/date_time.py
gcpy/file_regrid.py
gcpy/grid.py
gcpy/grid_stretching_transforms.py
gcpy/raveller_1D.py
gcpy/regrid.py
gcpy/regrid_restart_file.py
gcpy/units.py
gcpy/util.py
gcpy/benchmark/README.md
gcpy/benchmark/__init__.py
gcpy/benchmark/benchmark_slurm.sh
gcpy/benchmark/run_benchmark.py
gcpy/benchmark/cloud/README.md
gcpy/benchmark/cloud/template.1hr_benchmark.yml
gcpy/benchmark/cloud/template.1mo_benchmark.yml
gcpy/benchmark/config/1mo_benchmark.yml
gcpy/benchmark/config/1yr_ch4_benchmark.yml
gcpy/benchmark/config/1yr_fullchem_benchmark.yml
gcpy/benchmark/config/1yr_tt_benchmark.yml
gcpy/benchmark/config/README.md
gcpy/benchmark/modules/GC_72_vertical_levels.csv
gcpy/benchmark/modules/README.md
gcpy/benchmark/modules/__init__.py
gcpy/benchmark/modules/aod_species.yml
gcpy/benchmark/modules/benchmark_categories.yml
gcpy/benchmark/modules/benchmark_drydep.py
gcpy/benchmark/modules/benchmark_funcs.py
gcpy/benchmark/modules/benchmark_gcclassic_stats.py
gcpy/benchmark/modules/benchmark_mass_cons_table.py
gcpy/benchmark/modules/benchmark_models_vs_obs.py
gcpy/benchmark/modules/benchmark_models_vs_sondes.py
gcpy/benchmark/modules/benchmark_scrape_gcclassic_timers.py
gcpy/benchmark/modules/benchmark_scrape_gchp_timers.py
gcpy/benchmark/modules/benchmark_species_changes.py
gcpy/benchmark/modules/benchmark_utils.py
gcpy/benchmark/modules/budget_ox.py
gcpy/benchmark/modules/budget_tt.py
gcpy/benchmark/modules/emission_inventories.yml
gcpy/benchmark/modules/emission_species.yml
gcpy/benchmark/modules/lumped_species.yml
gcpy/benchmark/modules/oh_metrics.py
gcpy/benchmark/modules/run_1yr_fullchem_benchmark.py
gcpy/benchmark/modules/run_1yr_tt_benchmark.py
gcpy/benchmark/modules/ste_flux.py
gcpy/community/README.md
gcpy/community/__init__.py
gcpy/community/create_obspack_coords_file.py
gcpy/community/format_hemco_data.py
gcpy/examples/README.md
geoschem_gcpy-1.6.2.dist-info/licenses/AUTHORS.txt
geoschem_gcpy-1.6.2.dist-info/licenses/LICENSE.txt
geoschem_gcpy-1.6.2.dist-info/METADATA
geoschem_gcpy-1.6.2.dist-info/WHEEL
geoschem_gcpy-1.6.2.dist-info/top_level.txt
geoschem_gcpy-1.6.2.dist-info/RECORD
