Metadata-Version: 2.4
Name: geoschem-gcpy
Version: 1.6.2
Home-page: https://github.com/geoschem/gcpy
Author: GEOS-Chem Support Team
Author-email: geos-chem-support@g.harvard.edu
Maintainer: GEOS-Chem Support Team
Maintainer-email: geos-chem-support@g.harvard.edu
License: MIT
Classifier: Development Status :: 5 - Production/Stable
Classifier: License :: OSI Approved :: MIT License
Classifier: Operating System :: OS Independent
Classifier: Intended Audience :: Science/Research
Classifier: Programming Language :: Python
Classifier: Programming Language :: Python :: 3.12
Classifier: Topic :: Scientific/Engineering
License-File: LICENSE.txt
License-File: AUTHORS.txt
Requires-Dist: cartopy==0.23.0
Requires-Dist: cf_xarray==0.9.1
Requires-Dist: dask==2025.3.0
Requires-Dist: esmf==8.6.1
Requires-Dist: esmpy==8.6.1
Requires-Dist: gridspec==0.1.0
Requires-Dist: ipython==8.25.0
Requires-Dist: joblib==1.4.2
Requires-Dist: jupyter==1.0.0
Requires-Dist: matplotlib==3.8.4
Requires-Dist: netcdf4==1.6.5
Requires-Dist: netcdf-fortran==4.6.1
Requires-Dist: numpy==1.26.4
Requires-Dist: pandas==2.2.2
Requires-Dist: pip==24.0
Requires-Dist: pylint==3.2.2
Requires-Dist: pyproj==3.6.1
Requires-Dist: python==3.12.0
Requires-Dist: pypdf==4.2.0
Requires-Dist: requests==2.32.4
Requires-Dist: scipy==1.13.1
Requires-Dist: sparselt==0.1.3
Requires-Dist: tabulate==0.9.0
Requires-Dist: tk==8.6.13
Requires-Dist: xarray==2024.5.0
Requires-Dist: xesmf==0.8.5
Dynamic: author
Dynamic: author-email
Dynamic: classifier
Dynamic: description
Dynamic: home-page
Dynamic: license
Dynamic: license-file
Dynamic: maintainer
Dynamic: maintainer-email
Dynamic: requires-dist
